foostache/__init__.py
foostache/__main__.py
foostache/filters.py
foostache/template.py
foostache/visitor.py
foostache/py3parser/FoostacheLexer.py
foostache/py3parser/FoostacheParser.py
foostache/py3parser/FoostacheParserListener.py
foostache/py3parser/FoostacheParserVisitor.py
foostache/py3parser/__init__.py
lib/foostache/__init__.py
lib/foostache/__main__.py
lib/foostache/filters.py
lib/foostache/template.py
lib/foostache/visitor.py
lib/foostache/py3parser/FoostacheLexer.py
lib/foostache/py3parser/FoostacheParser.py
lib/foostache/py3parser/FoostacheParserListener.py
lib/foostache/py3parser/FoostacheParserVisitor.py
lib/foostache/py3parser/__init__.py
foostache-1.3.0.dist-info/LICENSE
foostache-1.3.0.dist-info/METADATA
foostache-1.3.0.dist-info/WHEEL
foostache-1.3.0.dist-info/entry_points.txt
foostache-1.3.0.dist-info/top_level.txt
foostache-1.3.0.dist-info/RECORD
